{
  "name": "1054",
  "description": "",
  "alias": [],
  "input": "",
  "values": [],
  "code": "1054+",
  "type": "console",
  "editor": "",
  "versions": [
    "1.06",
    "1.07",
    "1.08",
    "1.10",
    "1.11",
    "1.14",
    "1.16",
    "1.17"
  ],
  "devices": [
    "MultispeQ 1"
  ],
  "time": {
    "modified": "2017-06-06T19:27:09+00:00",
    "created": "2017-06-06T19:27:09+00:00"
  },
  "deprecated": false,
  "url": "",
  "dependencies": [],
  "parent": "",
  "md5": "be448b3fd0298219ff8df93ef09e33ca"
}